Metadata-Version: 2.1
Name: swagger2case
Version: 0.0.2
Summary: Convert SWAGGER data to JSON testcases for HttpRunner.
Home-page: https://github.com/BSTester/swagger2case
Author: 贝克街的捉虫师
Author-email: forpeng@foxmail.com
License: MIT
Keywords: swagger converter json
Platform: UNKNOWN
Classifier: Development Status :: 3 - Alpha
Classifier: Programming Language :: Python :: 3.5
Classifier: Programming Language :: Python :: 3.6
Classifier: Programming Language :: Python :: 3.7
Classifier: Programming Language :: Python :: 3.8
Classifier: Programming Language :: Python :: 3.9
